mmeutils/__init__.py
mmeutils/__init__.pyi
mmeutils/common/__init__.py
mmeutils/common/__init__.pyi
mmeutils/datetime/__init__.py
mmeutils/datetime/__init__.pyi
mmeutils/decorators/__init__.py
mmeutils/decorators/__init__.pyi
mmeutils/errors/__init__.py
mmeutils/errors/__init__.pyi
mmeutils/errors/mp4.py
mmeutils/errors/mp4.pyi
mmeutils/fileio/__init__.py
mmeutils/fileio/__init__.pyi
mmeutils/fileio/ffmpeg.py
mmeutils/fileio/ffmpeg.pyi
mmeutils/fileio/mp4.py
mmeutils/fileio/mp4.pyi
mmeutils/text/__init__.py
mmeutils/text/__init__.pyi
mmeutils/textio/__init__.py
mmeutils/textio/__init__.pyi
mmeutils/timer/__init__.py
mmeutils/timer/__init__.pyi
mmeutils/web/__init__.py
mmeutils/web/__init__.pyi
mmeutils/web/http.py
mmeutils/web/http.pyi
mmeutils/web/m3u8.py
mmeutils/web/m3u8.pyi
mmeutils-0.4.2.dist-info/licenses/LICENSE.txt
mmeutils-0.4.2.dist-info/METADATA
mmeutils-0.4.2.dist-info/WHEEL
mmeutils-0.4.2.dist-info/top_level.txt
mmeutils-0.4.2.dist-info/RECORD
